buildah_wrapper/__init__.py
buildah_wrapper/buildah_wrapper.py
buildah_wrapper-1.0.0.0.dist-info/METADATA
buildah_wrapper-1.0.0.0.dist-info/WHEEL
buildah_wrapper-1.0.0.0.dist-info/entry_points.txt
buildah_wrapper-1.0.0.0.dist-info/licenses/LICENSE
buildah_wrapper-1.0.0.0.dist-info/RECORD
