Metadata-Version: 2.4
Name: buildah-wrapper
Version: 1.0.0.0
Summary: EpicMorg: Buildah-Compose Wrapper - CLI wrapper for buildah build system
Project-URL: Homepage, https://github.com/EpicMorg/buildah-wrapper
Project-URL: Documentation, https://github.com/EpicMorg/buildah-wrapper/blob/master/README.md
Project-URL: Repository, https://github.com/EpicMorg/buildah-wrapper.git
Project-URL: Bug Tracker, https://github.com/EpicMorg/buildah-wrapper/issues
Project-URL: Changelog, https://github.com/EpicMorg/buildah-wrapper/blob/master/CHANGELOG.md
Author-email: Travoltik <spitefuldragons@mail.ru>, Marry <okomarova@saber.games>, EpicMorg <developer@epicm.org>
Maintainer-email: Travoltik <spitefuldragons@mail.ru>, Marry <okomarova@saber.games>, EpicMorg <developer@epicm.org>
License: MIT License
License-File: LICENSE
Keywords: build,buildah,ci,docker,podman,wrapper
Classifier: License :: OSI Approved :: MIT License
Classifier: Operating System :: Unix
Classifier: Programming Language :: Python :: 3
Requires-Python: >=3.6
Requires-Dist: python-dotenv
Requires-Dist: pyyaml
